{"headers":{"date":"Mon, 10 Feb 2020 14:37:15 +0000","Date":"Mon, 10 Feb 2020 14:37:15 +0000","subject":"RE: [EXTERNAL] Re: Checking availability","Subject":"RE: [EXTERNAL] Re: Checking availability","in_reply_to":"<470260916.341052.1581210267361@mail.yahoo.com>","message_id":"<BL0PR0901MB3763A7A70DD6BA8559B84534B2190@BL0PR0901MB3763.namprd09.prod.outlook.com>","references":"<BY5PR09MB41975FD040366C49B71C080EB2040@BY5PR09MB4197.namprd09.prod.outlook.com> <707065031.530939.1580414806161@mail.yahoo.com> <BL0PR0901MB3763B7AEDA1BEEFDF28A46BDB2000@BL0PR0901MB3763.namprd09.prod.outlook.com> <1784530696.112427.1580809142511@mail.yahoo.com> <BL0PR0901MB3763EBD5DF1CCAADDB614E8DB2020@BL0PR0901MB3763.namprd09.prod.outlook.com> <2025190272.919004.1580916309522@mail.yahoo.com> <BL0PR0901MB37631C2B1CF49481180F7918B2020@BL0PR0901MB3763.namprd09.prod.outlook.com> <109278255.1125229.1580934193422@mail.yahoo.com> <BL0PR0901MB37630172618C86E125ECAD65B2020@BL0PR0901MB3763.namprd09.prod.outlook.com> <669542189.13994.1580939366623@mail.yahoo.com> <BL0PR0901MB376311881C54D908D47BF3A6B2020@BL0PR0901MB3763.namprd09.prod.outlook.com> <470260916.341052.1581210267361@mail.yahoo.com>","toaddress":"Juana Harris <juanaharrisdht@att.net>","to":[{"personal":"Juana Harris","mailbox":"juanaharrisdht","host":"att.net"}],"fromaddress":"\"McKnight, Jules\" <jmcknight@presidiotrust.gov>","from":[{"personal":"McKnight, Jules","mailbox":"jmcknight","host":"presidiotrust.gov"}],"reply_toaddress":"\"McKnight, Jules\" <jmcknight@presidiotrust.gov>","reply_to":[{"personal":"McKnight, Jules","mailbox":"jmcknight","host":"presidiotrust.gov"}],"senderaddress":"\"McKnight, Jules\" <jmcknight@presidiotrust.gov>","sender":[{"personal":"McKnight, Jules","mailbox":"jmcknight","host":"presidiotrust.gov"}],"Recent":"N","Unseen":" ","Flagged":" ","Answered":" ","Deleted":" ","Draft":" ","Msgno":"35239","MailDate":"10-Feb-2020 14:37:15 +0000","Size":"137509","udate":1581345435}}