{"headers":{"date":"Mon, 10 Feb 2020 18:03:14 +0000","Date":"Mon, 10 Feb 2020 18:03:14 +0000","subject":"PO # 101023","Subject":"PO # 101023","message_id":"<MWHPR0401MB3532B49C67BEBC52536378C1DA190@MWHPR0401MB3532.namprd04.prod.outlook.com>","toaddress":"\"juanaharrisdht@att.net\" <juanaharrisdht@att.net>","to":[{"personal":"juanaharrisdht@att.net","mailbox":"juanaharrisdht","host":"att.net"}],"fromaddress":"Leticia Iavarone <liavarone@srcs.org>","from":[{"personal":"Leticia Iavarone","mailbox":"liavarone","host":"srcs.org"}],"reply_toaddress":"Leticia Iavarone <liavarone@srcs.org>","reply_to":[{"personal":"Leticia Iavarone","mailbox":"liavarone","host":"srcs.org"}],"senderaddress":"Leticia Iavarone <liavarone@srcs.org>","sender":[{"personal":"Leticia Iavarone","mailbox":"liavarone","host":"srcs.org"}],"Recent":"N","Unseen":" ","Flagged":" ","Answered":" ","Deleted":" ","Draft":" ","Msgno":"35252","MailDate":"10-Feb-2020 18:03:14 +0000","Size":"406926","udate":1581357794}}