{"headers":{"date":"Mon, 10 Feb 2020 13:19:29 -0800","Date":"Mon, 10 Feb 2020 13:19:29 -0800","subject":"Fwd: CORRECTION","Subject":"Fwd: CORRECTION","in_reply_to":"<CAPQEQ+h4u1Wxhg3apW12s79gWdmJfqeHBD9ok1gx9edTYrP-jw@mail.gmail.com>","message_id":"<CAPQEQ+hjZD_FE16RO=eZ9E5Kj1Ss0uFR4hdQpeMH819qFO_fvg@mail.gmail.com>","references":"<CAPQEQ+h4u1Wxhg3apW12s79gWdmJfqeHBD9ok1gx9edTYrP-jw@mail.gmail.com>","toaddress":"Juana Harris <juanaharrisdht@att.net>","to":[{"personal":"Juana Harris","mailbox":"juanaharrisdht","host":"att.net"}],"fromaddress":"\"Fonfa, Lynn\" <lynn_fonfa@nps.gov>","from":[{"personal":"Fonfa, Lynn","mailbox":"lynn_fonfa","host":"nps.gov"}],"reply_toaddress":"\"Fonfa, Lynn\" <lynn_fonfa@nps.gov>","reply_to":[{"personal":"Fonfa, Lynn","mailbox":"lynn_fonfa","host":"nps.gov"}],"senderaddress":"\"Fonfa, Lynn\" <lynn_fonfa@nps.gov>","sender":[{"personal":"Fonfa, Lynn","mailbox":"lynn_fonfa","host":"nps.gov"}],"Recent":"N","Unseen":" ","Flagged":" ","Answered":" ","Deleted":" ","Draft":" ","Msgno":"35265","MailDate":"10-Feb-2020 13:19:29 -0800","Size":"12679","udate":1581369569}}