{"headers":{"date":"Tue, 11 Feb 2020 13:48:13 -0800","Date":"Tue, 11 Feb 2020 13:48:13 -0800","subject":"Re: Court in Santa Cruz, Patrick Peterson","Subject":"Re: Court in Santa Cruz, Patrick Peterson","in_reply_to":"<A8EF5B07-96ED-44CB-965A-89F53AEFDADD@att.net>","message_id":"<4f9f1c41-898a-9d71-384d-87a73274797b@cruzio.com>","references":"<f91de0cd-d917-1859-e38d-741ded64d720@cruzio.com> <A8EF5B07-96ED-44CB-965A-89F53AEFDADD@att.net>","toaddress":"Juana Harris <juanaharrisdht@att.net>","to":[{"personal":"Juana Harris","mailbox":"juanaharrisdht","host":"att.net"}],"fromaddress":"James Danaher <danaher@cruzio.com>","from":[{"personal":"James Danaher","mailbox":"danaher","host":"cruzio.com"}],"reply_toaddress":"James Danaher <danaher@cruzio.com>","reply_to":[{"personal":"James Danaher","mailbox":"danaher","host":"cruzio.com"}],"senderaddress":"James Danaher <danaher@cruzio.com>","sender":[{"personal":"James Danaher","mailbox":"danaher","host":"cruzio.com"}],"Recent":"N","Unseen":" ","Flagged":" ","Answered":" ","Deleted":" ","Draft":" ","Msgno":"35289","MailDate":"11-Feb-2020 13:48:13 -0800","Size":"8080","udate":1581457693}}