{"headers":{"date":"Wed, 12 Feb 2020 15:16:56 -0800","Date":"Wed, 12 Feb 2020 15:16:56 -0800","subject":"Rescheduling Trip 22113","Subject":"Rescheduling Trip 22113","message_id":"<CAK4Chckif3EKWTPUv2B2iWdUkByEj2vpwxCbi7+sb6YEsu743Q@mail.gmail.com>","toaddress":"Juana Harris <juanaharrisdht@att.net>","to":[{"personal":"Juana Harris","mailbox":"juanaharrisdht","host":"att.net"}],"fromaddress":"Anne Bremer <anne@thewatershedproject.org>","from":[{"personal":"Anne Bremer","mailbox":"anne","host":"thewatershedproject.org"}],"reply_toaddress":"Anne Bremer <anne@thewatershedproject.org>","reply_to":[{"personal":"Anne Bremer","mailbox":"anne","host":"thewatershedproject.org"}],"senderaddress":"Anne Bremer <anne@thewatershedproject.org>","sender":[{"personal":"Anne Bremer","mailbox":"anne","host":"thewatershedproject.org"}],"Recent":"N","Unseen":" ","Flagged":" ","Answered":" ","Deleted":" ","Draft":" ","Msgno":"35342","MailDate":"12-Feb-2020 15:16:56 -0800","Size":"10953","udate":1581549416}}