{"headers":{"date":"Fri, 14 Feb 2020 14:00:40 -0800","Date":"Fri, 14 Feb 2020 14:00:40 -0800","subject":"Re: Field Trip transportation quote","Subject":"Re: Field Trip transportation quote","in_reply_to":"<1753788977.2449816.1581563338743@mail.yahoo.com>","message_id":"<CAJ0Yuaks8Sg5Ladui_jUG=sm3ZMHUQExS31+DfDipKQHa-npFA@mail.gmail.com>","references":"<CAJ0Yua=PkkzY6tdeH8apOBs_4zgw_xqF=RJPAOu2M4y-tmcyoA@mail.gmail.com> <1753788977.2449816.1581563338743@mail.yahoo.com>","toaddress":"Juana Harris <juanaharrisdht@att.net>","to":[{"personal":"Juana Harris","mailbox":"juanaharrisdht","host":"att.net"}],"fromaddress":"Edgar Mosqueda <edgar.mosqueda@wccusd.net>","from":[{"personal":"Edgar Mosqueda","mailbox":"edgar.mosqueda","host":"wccusd.net"}],"reply_toaddress":"Edgar Mosqueda <edgar.mosqueda@wccusd.net>","reply_to":[{"personal":"Edgar Mosqueda","mailbox":"edgar.mosqueda","host":"wccusd.net"}],"senderaddress":"Edgar Mosqueda <edgar.mosqueda@wccusd.net>","sender":[{"personal":"Edgar Mosqueda","mailbox":"edgar.mosqueda","host":"wccusd.net"}],"Recent":"N","Unseen":" ","Flagged":" ","Answered":" ","Deleted":" ","Draft":" ","Msgno":"35410","MailDate":"14-Feb-2020 14:00:40 -0800","Size":"14204","udate":1581717640}}