{"OrderID":{"type":"char(30)","field":"OrderID","null":0,"default":null,"key":"","oem":{"TABLE_QUALIFIER":"eComm","TABLE_OWNER":"dbo","TABLE_NAME":"Orders","COLUMN_NAME":"OrderID","DATA_TYPE":1,"TYPE_NAME":"char","PRECISION":30,"LENGTH":30,"SCALE":null,"RADIX":null,"NULLABLE":0,"REMARKS":null,"COLUMN_DEF":null,"SQL_DATA_TYPE":1,"SQL_DATETIME_SUB":null,"CHAR_OCTET_LENGTH":30,"ORDINAL_POSITION":1,"IS_NULLABLE":"NO ","SS_DATA_TYPE":47}},"OrderDate":{"type":"smalldatetime(16)","field":"OrderDate","null":0,"default":null,"key":"","oem":{"TABLE_QUALIFIER":"eComm","TABLE_OWNER":"dbo","TABLE_NAME":"Orders","COLUMN_NAME":"OrderDate","DATA_TYPE":11,"TYPE_NAME":"smalldatetime","PRECISION":16,"LENGTH":16,"SCALE":0,"RADIX":null,"NULLABLE":0,"REMARKS":null,"COLUMN_DEF":null,"SQL_DATA_TYPE":9,"SQL_DATETIME_SUB":3,"CHAR_OCTET_LENGTH":null,"ORDINAL_POSITION":2,"IS_NULLABLE":"NO ","SS_DATA_TYPE":58}},"ExpShipDate":{"type":"smalldatetime(16)","field":"ExpShipDate","null":1,"default":null,"key":"","oem":{"TABLE_QUALIFIER":"eComm","TABLE_OWNER":"dbo","TABLE_NAME":"Orders","COLUMN_NAME":"ExpShipDate","DATA_TYPE":11,"TYPE_NAME":"smalldatetime","PRECISION":16,"LENGTH":16,"SCALE":0,"RADIX":null,"NULLABLE":1,"REMARKS":null,"COLUMN_DEF":null,"SQL_DATA_TYPE":9,"SQL_DATETIME_SUB":3,"CHAR_OCTET_LENGTH":null,"ORDINAL_POSITION":3,"IS_NULLABLE":"YES","SS_DATA_TYPE":111}},"ActShipDate":{"type":"smalldatetime(16)","field":"ActShipDate","null":1,"default":null,"key":"","oem":{"TABLE_QUALIFIER":"eComm","TABLE_OWNER":"dbo","TABLE_NAME":"Orders","COLUMN_NAME":"ActShipDate","DATA_TYPE":11,"TYPE_NAME":"smalldatetime","PRECISION":16,"LENGTH":16,"SCALE":0,"RADIX":null,"NULLABLE":1,"REMARKS":null,"COLUMN_DEF":null,"SQL_DATA_TYPE":9,"SQL_DATETIME_SUB":3,"CHAR_OCTET_LENGTH":null,"ORDINAL_POSITION":4,"IS_NULLABLE":"YES","SS_DATA_TYPE":111}},"CustID":{"type":"char(20)","field":"CustID","null":0,"default":null,"key":"","oem":{"TABLE_QUALIFIER":"eComm","TABLE_OWNER":"dbo","TABLE_NAME":"Orders","COLUMN_NAME":"CustID","DATA_TYPE":1,"TYPE_NAME":"char","PRECISION":20,"LENGTH":20,"SCALE":null,"RADIX":null,"NULLABLE":0,"REMARKS":null,"COLUMN_DEF":null,"SQL_DATA_TYPE":1,"SQL_DATETIME_SUB":null,"CHAR_OCTET_LENGTH":20,"ORDINAL_POSITION":5,"IS_NULLABLE":"NO ","SS_DATA_TYPE":47}},"CustPONumber":{"type":"char(20)","field":"CustPONumber","null":1,"default":null,"key":"","oem":{"TABLE_QUALIFIER":"eComm","TABLE_OWNER":"dbo","TABLE_NAME":"Orders","COLUMN_NAME":"CustPONumber","DATA_TYPE":1,"TYPE_NAME":"char","PRECISION":20,"LENGTH":20,"SCALE":null,"RADIX":null,"NULLABLE":1,"REMARKS":null,"COLUMN_DEF":null,"SQL_DATA_TYPE":1,"SQL_DATETIME_SUB":null,"CHAR_OCTET_LENGTH":20,"ORDINAL_POSITION":6,"IS_NULLABLE":"YES","SS_DATA_TYPE":39}},"Status":{"type":"char(6)","field":"Status","null":0,"default":null,"key":"","oem":{"TABLE_QUALIFIER":"eComm","TABLE_OWNER":"dbo","TABLE_NAME":"Orders","COLUMN_NAME":"Status","DATA_TYPE":1,"TYPE_NAME":"char","PRECISION":6,"LENGTH":6,"SCALE":null,"RADIX":null,"NULLABLE":0,"REMARKS":null,"COLUMN_DEF":null,"SQL_DATA_TYPE":1,"SQL_DATETIME_SUB":null,"CHAR_OCTET_LENGTH":6,"ORDINAL_POSITION":7,"IS_NULLABLE":"NO ","SS_DATA_TYPE":47}},"FOB":{"type":"char(15)","field":"FOB","null":1,"default":null,"key":"","oem":{"TABLE_QUALIFIER":"eComm","TABLE_OWNER":"dbo","TABLE_NAME":"Orders","COLUMN_NAME":"FOB","DATA_TYPE":1,"TYPE_NAME":"char","PRECISION":15,"LENGTH":15,"SCALE":null,"RADIX":null,"NULLABLE":1,"REMARKS":null,"COLUMN_DEF":null,"SQL_DATA_TYPE":1,"SQL_DATETIME_SUB":null,"CHAR_OCTET_LENGTH":15,"ORDINAL_POSITION":8,"IS_NULLABLE":"YES","SS_DATA_TYPE":39}},"Freight":{"type":"decimal(12, 2)","field":"Freight","null":1,"default":null,"key":"","oem":{"TABLE_QUALIFIER":"eComm","TABLE_OWNER":"dbo","TABLE_NAME":"Orders","COLUMN_NAME":"Freight","DATA_TYPE":3,"TYPE_NAME":"decimal","PRECISION":10,"LENGTH":12,"SCALE":2,"RADIX":10,"NULLABLE":1,"REMARKS":null,"COLUMN_DEF":null,"SQL_DATA_TYPE":3,"SQL_DATETIME_SUB":null,"CHAR_OCTET_LENGTH":null,"ORDINAL_POSITION":9,"IS_NULLABLE":"YES","SS_DATA_TYPE":106}},"ShipPriority":{"type":"int(4)","field":"ShipPriority","null":1,"default":null,"key":"","oem":{"TABLE_QUALIFIER":"eComm","TABLE_OWNER":"dbo","TABLE_NAME":"Orders","COLUMN_NAME":"ShipPriority","DATA_TYPE":4,"TYPE_NAME":"int","PRECISION":10,"LENGTH":4,"SCALE":0,"RADIX":10,"NULLABLE":1,"REMARKS":null,"COLUMN_DEF":null,"SQL_DATA_TYPE":4,"SQL_DATETIME_SUB":null,"CHAR_OCTET_LENGTH":null,"ORDINAL_POSITION":10,"IS_NULLABLE":"YES","SS_DATA_TYPE":38}},"LastLineNumber":{"type":"int(4)","field":"LastLineNumber","null":0,"default":null,"key":"","oem":{"TABLE_QUALIFIER":"eComm","TABLE_OWNER":"dbo","TABLE_NAME":"Orders","COLUMN_NAME":"LastLineNumber","DATA_TYPE":4,"TYPE_NAME":"int","PRECISION":10,"LENGTH":4,"SCALE":0,"RADIX":10,"NULLABLE":0,"REMARKS":null,"COLUMN_DEF":null,"SQL_DATA_TYPE":4,"SQL_DATETIME_SUB":null,"CHAR_OCTET_LENGTH":null,"ORDINAL_POSITION":11,"IS_NULLABLE":"NO ","SS_DATA_TYPE":56}},"ShipName":{"type":"char(40)","field":"ShipName","null":1,"default":null,"key":"","oem":{"TABLE_QUALIFIER":"eComm","TABLE_OWNER":"dbo","TABLE_NAME":"Orders","COLUMN_NAME":"ShipName","DATA_TYPE":1,"TYPE_NAME":"char","PRECISION":40,"LENGTH":40,"SCALE":null,"RADIX":null,"NULLABLE":1,"REMARKS":null,"COLUMN_DEF":null,"SQL_DATA_TYPE":1,"SQL_DATETIME_SUB":null,"CHAR_OCTET_LENGTH":40,"ORDINAL_POSITION":12,"IS_NULLABLE":"YES","SS_DATA_TYPE":39}},"ShipAddr1":{"type":"char(40)","field":"ShipAddr1","null":1,"default":null,"key":"","oem":{"TABLE_QUALIFIER":"eComm","TABLE_OWNER":"dbo","TABLE_NAME":"Orders","COLUMN_NAME":"ShipAddr1","DATA_TYPE":1,"TYPE_NAME":"char","PRECISION":40,"LENGTH":40,"SCALE":null,"RADIX":null,"NULLABLE":1,"REMARKS":null,"COLUMN_DEF":null,"SQL_DATA_TYPE":1,"SQL_DATETIME_SUB":null,"CHAR_OCTET_LENGTH":40,"ORDINAL_POSITION":13,"IS_NULLABLE":"YES","SS_DATA_TYPE":39}},"ShipAddr2":{"type":"char(40)","field":"ShipAddr2","null":1,"default":null,"key":"","oem":{"TABLE_QUALIFIER":"eComm","TABLE_OWNER":"dbo","TABLE_NAME":"Orders","COLUMN_NAME":"ShipAddr2","DATA_TYPE":1,"TYPE_NAME":"char","PRECISION":40,"LENGTH":40,"SCALE":null,"RADIX":null,"NULLABLE":1,"REMARKS":null,"COLUMN_DEF":null,"SQL_DATA_TYPE":1,"SQL_DATETIME_SUB":null,"CHAR_OCTET_LENGTH":40,"ORDINAL_POSITION":14,"IS_NULLABLE":"YES","SS_DATA_TYPE":39}},"ShipCity":{"type":"char(20)","field":"ShipCity","null":1,"default":null,"key":"","oem":{"TABLE_QUALIFIER":"eComm","TABLE_OWNER":"dbo","TABLE_NAME":"Orders","COLUMN_NAME":"ShipCity","DATA_TYPE":1,"TYPE_NAME":"char","PRECISION":20,"LENGTH":20,"SCALE":null,"RADIX":null,"NULLABLE":1,"REMARKS":null,"COLUMN_DEF":null,"SQL_DATA_TYPE":1,"SQL_DATETIME_SUB":null,"CHAR_OCTET_LENGTH":20,"ORDINAL_POSITION":15,"IS_NULLABLE":"YES","SS_DATA_TYPE":39}},"ShipState":{"type":"char(2)","field":"ShipState","null":1,"default":null,"key":"","oem":{"TABLE_QUALIFIER":"eComm","TABLE_OWNER":"dbo","TABLE_NAME":"Orders","COLUMN_NAME":"ShipState","DATA_TYPE":1,"TYPE_NAME":"char","PRECISION":2,"LENGTH":2,"SCALE":null,"RADIX":null,"NULLABLE":1,"REMARKS":null,"COLUMN_DEF":null,"SQL_DATA_TYPE":1,"SQL_DATETIME_SUB":null,"CHAR_OCTET_LENGTH":2,"ORDINAL_POSITION":16,"IS_NULLABLE":"YES","SS_DATA_TYPE":39}},"ShipZip":{"type":"char(9)","field":"ShipZip","null":1,"default":null,"key":"","oem":{"TABLE_QUALIFIER":"eComm","TABLE_OWNER":"dbo","TABLE_NAME":"Orders","COLUMN_NAME":"ShipZip","DATA_TYPE":1,"TYPE_NAME":"char","PRECISION":9,"LENGTH":9,"SCALE":null,"RADIX":null,"NULLABLE":1,"REMARKS":null,"COLUMN_DEF":null,"SQL_DATA_TYPE":1,"SQL_DATETIME_SUB":null,"CHAR_OCTET_LENGTH":9,"ORDINAL_POSITION":17,"IS_NULLABLE":"YES","SS_DATA_TYPE":39}},"ShipComplete":{"type":"bit(1)","field":"ShipComplete","null":0,"default":null,"key":"","oem":{"TABLE_QUALIFIER":"eComm","TABLE_OWNER":"dbo","TABLE_NAME":"Orders","COLUMN_NAME":"ShipComplete","DATA_TYPE":-7,"TYPE_NAME":"bit","PRECISION":1,"LENGTH":1,"SCALE":0,"RADIX":null,"NULLABLE":0,"REMARKS":null,"COLUMN_DEF":null,"SQL_DATA_TYPE":-7,"SQL_DATETIME_SUB":null,"CHAR_OCTET_LENGTH":null,"ORDINAL_POSITION":18,"IS_NULLABLE":"NO ","SS_DATA_TYPE":50}},"TypeCode":{"type":"varchar(20)","field":"TypeCode","null":1,"default":null,"key":"","oem":{"TABLE_QUALIFIER":"eComm","TABLE_OWNER":"dbo","TABLE_NAME":"Orders","COLUMN_NAME":"TypeCode","DATA_TYPE":12,"TYPE_NAME":"varchar","PRECISION":20,"LENGTH":20,"SCALE":null,"RADIX":null,"NULLABLE":1,"REMARKS":null,"COLUMN_DEF":null,"SQL_DATA_TYPE":12,"SQL_DATETIME_SUB":null,"CHAR_OCTET_LENGTH":20,"ORDINAL_POSITION":19,"IS_NULLABLE":"YES","SS_DATA_TYPE":39}},"User1":{"type":"char(30)","field":"User1","null":1,"default":null,"key":"","oem":{"TABLE_QUALIFIER":"eComm","TABLE_OWNER":"dbo","TABLE_NAME":"Orders","COLUMN_NAME":"User1","DATA_TYPE":1,"TYPE_NAME":"char","PRECISION":30,"LENGTH":30,"SCALE":null,"RADIX":null,"NULLABLE":1,"REMARKS":null,"COLUMN_DEF":null,"SQL_DATA_TYPE":1,"SQL_DATETIME_SUB":null,"CHAR_OCTET_LENGTH":30,"ORDINAL_POSITION":20,"IS_NULLABLE":"YES","SS_DATA_TYPE":39}},"User2":{"type":"char(30)","field":"User2","null":1,"default":null,"key":"","oem":{"TABLE_QUALIFIER":"eComm","TABLE_OWNER":"dbo","TABLE_NAME":"Orders","COLUMN_NAME":"User2","DATA_TYPE":1,"TYPE_NAME":"char","PRECISION":30,"LENGTH":30,"SCALE":null,"RADIX":null,"NULLABLE":1,"REMARKS":null,"COLUMN_DEF":null,"SQL_DATA_TYPE":1,"SQL_DATETIME_SUB":null,"CHAR_OCTET_LENGTH":30,"ORDINAL_POSITION":21,"IS_NULLABLE":"YES","SS_DATA_TYPE":39}},"User3":{"type":"decimal(20)","field":"User3","null":1,"default":null,"key":"","oem":{"TABLE_QUALIFIER":"eComm","TABLE_OWNER":"dbo","TABLE_NAME":"Orders","COLUMN_NAME":"User3","DATA_TYPE":3,"TYPE_NAME":"decimal","PRECISION":18,"LENGTH":20,"SCALE":0,"RADIX":10,"NULLABLE":1,"REMARKS":null,"COLUMN_DEF":null,"SQL_DATA_TYPE":3,"SQL_DATETIME_SUB":null,"CHAR_OCTET_LENGTH":null,"ORDINAL_POSITION":22,"IS_NULLABLE":"YES","SS_DATA_TYPE":106}},"User4":{"type":"decimal(20)","field":"User4","null":1,"default":null,"key":"","oem":{"TABLE_QUALIFIER":"eComm","TABLE_OWNER":"dbo","TABLE_NAME":"Orders","COLUMN_NAME":"User4","DATA_TYPE":3,"TYPE_NAME":"decimal","PRECISION":18,"LENGTH":20,"SCALE":0,"RADIX":10,"NULLABLE":1,"REMARKS":null,"COLUMN_DEF":null,"SQL_DATA_TYPE":3,"SQL_DATETIME_SUB":null,"CHAR_OCTET_LENGTH":null,"ORDINAL_POSITION":23,"IS_NULLABLE":"YES","SS_DATA_TYPE":106}},"AllocDate":{"type":"smalldatetime(16)","field":"AllocDate","null":1,"default":null,"key":"","oem":{"TABLE_QUALIFIER":"eComm","TABLE_OWNER":"dbo","TABLE_NAME":"Orders","COLUMN_NAME":"AllocDate","DATA_TYPE":11,"TYPE_NAME":"smalldatetime","PRECISION":16,"LENGTH":16,"SCALE":0,"RADIX":null,"NULLABLE":1,"REMARKS":null,"COLUMN_DEF":null,"SQL_DATA_TYPE":9,"SQL_DATETIME_SUB":3,"CHAR_OCTET_LENGTH":null,"ORDINAL_POSITION":24,"IS_NULLABLE":"YES","SS_DATA_TYPE":111}},"AllocTime":{"type":"smalldatetime(16)","field":"AllocTime","null":1,"default":null,"key":"","oem":{"TABLE_QUALIFIER":"eComm","TABLE_OWNER":"dbo","TABLE_NAME":"Orders","COLUMN_NAME":"AllocTime","DATA_TYPE":11,"TYPE_NAME":"smalldatetime","PRECISION":16,"LENGTH":16,"SCALE":0,"RADIX":null,"NULLABLE":1,"REMARKS":null,"COLUMN_DEF":null,"SQL_DATA_TYPE":9,"SQL_DATETIME_SUB":3,"CHAR_OCTET_LENGTH":null,"ORDINAL_POSITION":25,"IS_NULLABLE":"YES","SS_DATA_TYPE":111}},"AllocOperID":{"type":"char(10)","field":"AllocOperID","null":1,"default":null,"key":"","oem":{"TABLE_QUALIFIER":"eComm","TABLE_OWNER":"dbo","TABLE_NAME":"Orders","COLUMN_NAME":"AllocOperID","DATA_TYPE":1,"TYPE_NAME":"char","PRECISION":10,"LENGTH":10,"SCALE":null,"RADIX":null,"NULLABLE":1,"REMARKS":null,"COLUMN_DEF":null,"SQL_DATA_TYPE":1,"SQL_DATETIME_SUB":null,"CHAR_OCTET_LENGTH":10,"ORDINAL_POSITION":26,"IS_NULLABLE":"YES","SS_DATA_TYPE":39}},"PickDate":{"type":"smalldatetime(16)","field":"PickDate","null":1,"default":null,"key":"","oem":{"TABLE_QUALIFIER":"eComm","TABLE_OWNER":"dbo","TABLE_NAME":"Orders","COLUMN_NAME":"PickDate","DATA_TYPE":11,"TYPE_NAME":"smalldatetime","PRECISION":16,"LENGTH":16,"SCALE":0,"RADIX":null,"NULLABLE":1,"REMARKS":null,"COLUMN_DEF":null,"SQL_DATA_TYPE":9,"SQL_DATETIME_SUB":3,"CHAR_OCTET_LENGTH":null,"ORDINAL_POSITION":27,"IS_NULLABLE":"YES","SS_DATA_TYPE":111}},"PickTime":{"type":"smalldatetime(16)","field":"PickTime","null":1,"default":null,"key":"","oem":{"TABLE_QUALIFIER":"eComm","TABLE_OWNER":"dbo","TABLE_NAME":"Orders","COLUMN_NAME":"PickTime","DATA_TYPE":11,"TYPE_NAME":"smalldatetime","PRECISION":16,"LENGTH":16,"SCALE":0,"RADIX":null,"NULLABLE":1,"REMARKS":null,"COLUMN_DEF":null,"SQL_DATA_TYPE":9,"SQL_DATETIME_SUB":3,"CHAR_OCTET_LENGTH":null,"ORDINAL_POSITION":28,"IS_NULLABLE":"YES","SS_DATA_TYPE":111}},"PickOperID":{"type":"char(10)","field":"PickOperID","null":1,"default":null,"key":"","oem":{"TABLE_QUALIFIER":"eComm","TABLE_OWNER":"dbo","TABLE_NAME":"Orders","COLUMN_NAME":"PickOperID","DATA_TYPE":1,"TYPE_NAME":"char","PRECISION":10,"LENGTH":10,"SCALE":null,"RADIX":null,"NULLABLE":1,"REMARKS":null,"COLUMN_DEF":null,"SQL_DATA_TYPE":1,"SQL_DATETIME_SUB":null,"CHAR_OCTET_LENGTH":10,"ORDINAL_POSITION":29,"IS_NULLABLE":"YES","SS_DATA_TYPE":39}},"PackDate":{"type":"smalldatetime(16)","field":"PackDate","null":1,"default":null,"key":"","oem":{"TABLE_QUALIFIER":"eComm","TABLE_OWNER":"dbo","TABLE_NAME":"Orders","COLUMN_NAME":"PackDate","DATA_TYPE":11,"TYPE_NAME":"smalldatetime","PRECISION":16,"LENGTH":16,"SCALE":0,"RADIX":null,"NULLABLE":1,"REMARKS":null,"COLUMN_DEF":null,"SQL_DATA_TYPE":9,"SQL_DATETIME_SUB":3,"CHAR_OCTET_LENGTH":null,"ORDINAL_POSITION":30,"IS_NULLABLE":"YES","SS_DATA_TYPE":111}},"PackTime":{"type":"smalldatetime(16)","field":"PackTime","null":1,"default":null,"key":"","oem":{"TABLE_QUALIFIER":"eComm","TABLE_OWNER":"dbo","TABLE_NAME":"Orders","COLUMN_NAME":"PackTime","DATA_TYPE":11,"TYPE_NAME":"smalldatetime","PRECISION":16,"LENGTH":16,"SCALE":0,"RADIX":null,"NULLABLE":1,"REMARKS":null,"COLUMN_DEF":null,"SQL_DATA_TYPE":9,"SQL_DATETIME_SUB":3,"CHAR_OCTET_LENGTH":null,"ORDINAL_POSITION":31,"IS_NULLABLE":"YES","SS_DATA_TYPE":111}},"PackOperID":{"type":"char(10)","field":"PackOperID","null":1,"default":null,"key":"","oem":{"TABLE_QUALIFIER":"eComm","TABLE_OWNER":"dbo","TABLE_NAME":"Orders","COLUMN_NAME":"PackOperID","DATA_TYPE":1,"TYPE_NAME":"char","PRECISION":10,"LENGTH":10,"SCALE":null,"RADIX":null,"NULLABLE":1,"REMARKS":null,"COLUMN_DEF":null,"SQL_DATA_TYPE":1,"SQL_DATETIME_SUB":null,"CHAR_OCTET_LENGTH":10,"ORDINAL_POSITION":32,"IS_NULLABLE":"YES","SS_DATA_TYPE":39}},"ShipDate":{"type":"smalldatetime(16)","field":"ShipDate","null":1,"default":null,"key":"","oem":{"TABLE_QUALIFIER":"eComm","TABLE_OWNER":"dbo","TABLE_NAME":"Orders","COLUMN_NAME":"ShipDate","DATA_TYPE":11,"TYPE_NAME":"smalldatetime","PRECISION":16,"LENGTH":16,"SCALE":0,"RADIX":null,"NULLABLE":1,"REMARKS":null,"COLUMN_DEF":null,"SQL_DATA_TYPE":9,"SQL_DATETIME_SUB":3,"CHAR_OCTET_LENGTH":null,"ORDINAL_POSITION":33,"IS_NULLABLE":"YES","SS_DATA_TYPE":111}},"ShipTime":{"type":"smalldatetime(16)","field":"ShipTime","null":1,"default":null,"key":"","oem":{"TABLE_QUALIFIER":"eComm","TABLE_OWNER":"dbo","TABLE_NAME":"Orders","COLUMN_NAME":"ShipTime","DATA_TYPE":11,"TYPE_NAME":"smalldatetime","PRECISION":16,"LENGTH":16,"SCALE":0,"RADIX":null,"NULLABLE":1,"REMARKS":null,"COLUMN_DEF":null,"SQL_DATA_TYPE":9,"SQL_DATETIME_SUB":3,"CHAR_OCTET_LENGTH":null,"ORDINAL_POSITION":34,"IS_NULLABLE":"YES","SS_DATA_TYPE":111}},"ShipOperID":{"type":"char(10)","field":"ShipOperID","null":1,"default":null,"key":"","oem":{"TABLE_QUALIFIER":"eComm","TABLE_OWNER":"dbo","TABLE_NAME":"Orders","COLUMN_NAME":"ShipOperID","DATA_TYPE":1,"TYPE_NAME":"char","PRECISION":10,"LENGTH":10,"SCALE":null,"RADIX":null,"NULLABLE":1,"REMARKS":null,"COLUMN_DEF":null,"SQL_DATA_TYPE":1,"SQL_DATETIME_SUB":null,"CHAR_OCTET_LENGTH":10,"ORDINAL_POSITION":35,"IS_NULLABLE":"YES","SS_DATA_TYPE":39}},"DistName":{"type":"char(40)","field":"DistName","null":1,"default":null,"key":"","oem":{"TABLE_QUALIFIER":"eComm","TABLE_OWNER":"dbo","TABLE_NAME":"Orders","COLUMN_NAME":"DistName","DATA_TYPE":1,"TYPE_NAME":"char","PRECISION":40,"LENGTH":40,"SCALE":null,"RADIX":null,"NULLABLE":1,"REMARKS":null,"COLUMN_DEF":null,"SQL_DATA_TYPE":1,"SQL_DATETIME_SUB":null,"CHAR_OCTET_LENGTH":40,"ORDINAL_POSITION":36,"IS_NULLABLE":"YES","SS_DATA_TYPE":39}},"DistAddr1":{"type":"char(40)","field":"DistAddr1","null":1,"default":null,"key":"","oem":{"TABLE_QUALIFIER":"eComm","TABLE_OWNER":"dbo","TABLE_NAME":"Orders","COLUMN_NAME":"DistAddr1","DATA_TYPE":1,"TYPE_NAME":"char","PRECISION":40,"LENGTH":40,"SCALE":null,"RADIX":null,"NULLABLE":1,"REMARKS":null,"COLUMN_DEF":null,"SQL_DATA_TYPE":1,"SQL_DATETIME_SUB":null,"CHAR_OCTET_LENGTH":40,"ORDINAL_POSITION":37,"IS_NULLABLE":"YES","SS_DATA_TYPE":39}},"DistAddr2":{"type":"char(40)","field":"DistAddr2","null":1,"default":null,"key":"","oem":{"TABLE_QUALIFIER":"eComm","TABLE_OWNER":"dbo","TABLE_NAME":"Orders","COLUMN_NAME":"DistAddr2","DATA_TYPE":1,"TYPE_NAME":"char","PRECISION":40,"LENGTH":40,"SCALE":null,"RADIX":null,"NULLABLE":1,"REMARKS":null,"COLUMN_DEF":null,"SQL_DATA_TYPE":1,"SQL_DATETIME_SUB":null,"CHAR_OCTET_LENGTH":40,"ORDINAL_POSITION":38,"IS_NULLABLE":"YES","SS_DATA_TYPE":39}},"DistCity":{"type":"char(20)","field":"DistCity","null":1,"default":null,"key":"","oem":{"TABLE_QUALIFIER":"eComm","TABLE_OWNER":"dbo","TABLE_NAME":"Orders","COLUMN_NAME":"DistCity","DATA_TYPE":1,"TYPE_NAME":"char","PRECISION":20,"LENGTH":20,"SCALE":null,"RADIX":null,"NULLABLE":1,"REMARKS":null,"COLUMN_DEF":null,"SQL_DATA_TYPE":1,"SQL_DATETIME_SUB":null,"CHAR_OCTET_LENGTH":20,"ORDINAL_POSITION":39,"IS_NULLABLE":"YES","SS_DATA_TYPE":39}},"DistState":{"type":"char(2)","field":"DistState","null":1,"default":null,"key":"","oem":{"TABLE_QUALIFIER":"eComm","TABLE_OWNER":"dbo","TABLE_NAME":"Orders","COLUMN_NAME":"DistState","DATA_TYPE":1,"TYPE_NAME":"char","PRECISION":2,"LENGTH":2,"SCALE":null,"RADIX":null,"NULLABLE":1,"REMARKS":null,"COLUMN_DEF":null,"SQL_DATA_TYPE":1,"SQL_DATETIME_SUB":null,"CHAR_OCTET_LENGTH":2,"ORDINAL_POSITION":40,"IS_NULLABLE":"YES","SS_DATA_TYPE":39}},"DistZip":{"type":"char(9)","field":"DistZip","null":1,"default":null,"key":"","oem":{"TABLE_QUALIFIER":"eComm","TABLE_OWNER":"dbo","TABLE_NAME":"Orders","COLUMN_NAME":"DistZip","DATA_TYPE":1,"TYPE_NAME":"char","PRECISION":9,"LENGTH":9,"SCALE":null,"RADIX":null,"NULLABLE":1,"REMARKS":null,"COLUMN_DEF":null,"SQL_DATA_TYPE":1,"SQL_DATETIME_SUB":null,"CHAR_OCTET_LENGTH":9,"ORDINAL_POSITION":41,"IS_NULLABLE":"YES","SS_DATA_TYPE":39}},"LabelFormat":{"type":"char(20)","field":"LabelFormat","null":1,"default":null,"key":"","oem":{"TABLE_QUALIFIER":"eComm","TABLE_OWNER":"dbo","TABLE_NAME":"Orders","COLUMN_NAME":"LabelFormat","DATA_TYPE":1,"TYPE_NAME":"char","PRECISION":20,"LENGTH":20,"SCALE":null,"RADIX":null,"NULLABLE":1,"REMARKS":null,"COLUMN_DEF":null,"SQL_DATA_TYPE":1,"SQL_DATETIME_SUB":null,"CHAR_OCTET_LENGTH":20,"ORDINAL_POSITION":42,"IS_NULLABLE":"YES","SS_DATA_TYPE":39}},"ASNRequired":{"type":"bit(1)","field":"ASNRequired","null":0,"default":null,"key":"","oem":{"TABLE_QUALIFIER":"eComm","TABLE_OWNER":"dbo","TABLE_NAME":"Orders","COLUMN_NAME":"ASNRequired","DATA_TYPE":-7,"TYPE_NAME":"bit","PRECISION":1,"LENGTH":1,"SCALE":0,"RADIX":null,"NULLABLE":0,"REMARKS":null,"COLUMN_DEF":null,"SQL_DATA_TYPE":-7,"SQL_DATETIME_SUB":null,"CHAR_OCTET_LENGTH":null,"ORDINAL_POSITION":43,"IS_NULLABLE":"NO ","SS_DATA_TYPE":50}},"ASNSentDate":{"type":"smalldatetime(16)","field":"ASNSentDate","null":1,"default":null,"key":"","oem":{"TABLE_QUALIFIER":"eComm","TABLE_OWNER":"dbo","TABLE_NAME":"Orders","COLUMN_NAME":"ASNSentDate","DATA_TYPE":11,"TYPE_NAME":"smalldatetime","PRECISION":16,"LENGTH":16,"SCALE":0,"RADIX":null,"NULLABLE":1,"REMARKS":null,"COLUMN_DEF":null,"SQL_DATA_TYPE":9,"SQL_DATETIME_SUB":3,"CHAR_OCTET_LENGTH":null,"ORDINAL_POSITION":44,"IS_NULLABLE":"YES","SS_DATA_TYPE":111}},"ASNSentTime":{"type":"smalldatetime(16)","field":"ASNSentTime","null":1,"default":null,"key":"","oem":{"TABLE_QUALIFIER":"eComm","TABLE_OWNER":"dbo","TABLE_NAME":"Orders","COLUMN_NAME":"ASNSentTime","DATA_TYPE":11,"TYPE_NAME":"smalldatetime","PRECISION":16,"LENGTH":16,"SCALE":0,"RADIX":null,"NULLABLE":1,"REMARKS":null,"COLUMN_DEF":null,"SQL_DATA_TYPE":9,"SQL_DATETIME_SUB":3,"CHAR_OCTET_LENGTH":null,"ORDINAL_POSITION":45,"IS_NULLABLE":"YES","SS_DATA_TYPE":111}},"EDIPartnerID":{"type":"char(20)","field":"EDIPartnerID","null":1,"default":null,"key":"","oem":{"TABLE_QUALIFIER":"eComm","TABLE_OWNER":"dbo","TABLE_NAME":"Orders","COLUMN_NAME":"EDIPartnerID","DATA_TYPE":1,"TYPE_NAME":"char","PRECISION":20,"LENGTH":20,"SCALE":null,"RADIX":null,"NULLABLE":1,"REMARKS":null,"COLUMN_DEF":null,"SQL_DATA_TYPE":1,"SQL_DATETIME_SUB":null,"CHAR_OCTET_LENGTH":20,"ORDINAL_POSITION":46,"IS_NULLABLE":"YES","SS_DATA_TYPE":39}},"Note":{"type":"varchar(255)","field":"Note","null":1,"default":null,"key":"","oem":{"TABLE_QUALIFIER":"eComm","TABLE_OWNER":"dbo","TABLE_NAME":"Orders","COLUMN_NAME":"Note","DATA_TYPE":12,"TYPE_NAME":"varchar","PRECISION":255,"LENGTH":255,"SCALE":null,"RADIX":null,"NULLABLE":1,"REMARKS":null,"COLUMN_DEF":null,"SQL_DATA_TYPE":12,"SQL_DATETIME_SUB":null,"CHAR_OCTET_LENGTH":255,"ORDINAL_POSITION":47,"IS_NULLABLE":"YES","SS_DATA_TYPE":39}},"ShipTrackID":{"type":"char(30)","field":"ShipTrackID","null":1,"default":null,"key":"","oem":{"TABLE_QUALIFIER":"eComm","TABLE_OWNER":"dbo","TABLE_NAME":"Orders","COLUMN_NAME":"ShipTrackID","DATA_TYPE":1,"TYPE_NAME":"char","PRECISION":30,"LENGTH":30,"SCALE":null,"RADIX":null,"NULLABLE":1,"REMARKS":null,"COLUMN_DEF":null,"SQL_DATA_TYPE":1,"SQL_DATETIME_SUB":null,"CHAR_OCTET_LENGTH":30,"ORDINAL_POSITION":48,"IS_NULLABLE":"YES","SS_DATA_TYPE":39}},"BatchID":{"type":"char(10)","field":"BatchID","null":1,"default":null,"key":"","oem":{"TABLE_QUALIFIER":"eComm","TABLE_OWNER":"dbo","TABLE_NAME":"Orders","COLUMN_NAME":"BatchID","DATA_TYPE":1,"TYPE_NAME":"char","PRECISION":10,"LENGTH":10,"SCALE":null,"RADIX":null,"NULLABLE":1,"REMARKS":null,"COLUMN_DEF":null,"SQL_DATA_TYPE":1,"SQL_DATETIME_SUB":null,"CHAR_OCTET_LENGTH":10,"ORDINAL_POSITION":49,"IS_NULLABLE":"YES","SS_DATA_TYPE":39}},"ShipVia":{"type":"char(10)","field":"ShipVia","null":1,"default":null,"key":"","oem":{"TABLE_QUALIFIER":"eComm","TABLE_OWNER":"dbo","TABLE_NAME":"Orders","COLUMN_NAME":"ShipVia","DATA_TYPE":1,"TYPE_NAME":"char","PRECISION":10,"LENGTH":10,"SCALE":null,"RADIX":null,"NULLABLE":1,"REMARKS":null,"COLUMN_DEF":null,"SQL_DATA_TYPE":1,"SQL_DATETIME_SUB":null,"CHAR_OCTET_LENGTH":10,"ORDINAL_POSITION":50,"IS_NULLABLE":"YES","SS_DATA_TYPE":39}},"AllocZone":{"type":"varchar(20)","field":"AllocZone","null":1,"default":null,"key":"","oem":{"TABLE_QUALIFIER":"eComm","TABLE_OWNER":"dbo","TABLE_NAME":"Orders","COLUMN_NAME":"AllocZone","DATA_TYPE":12,"TYPE_NAME":"varchar","PRECISION":20,"LENGTH":20,"SCALE":null,"RADIX":null,"NULLABLE":1,"REMARKS":null,"COLUMN_DEF":null,"SQL_DATA_TYPE":12,"SQL_DATETIME_SUB":null,"CHAR_OCTET_LENGTH":20,"ORDINAL_POSITION":51,"IS_NULLABLE":"YES","SS_DATA_TYPE":39}},"User5":{"type":"varchar(30)","field":"User5","null":1,"default":null,"key":"","oem":{"TABLE_QUALIFIER":"eComm","TABLE_OWNER":"dbo","TABLE_NAME":"Orders","COLUMN_NAME":"User5","DATA_TYPE":12,"TYPE_NAME":"varchar","PRECISION":30,"LENGTH":30,"SCALE":null,"RADIX":null,"NULLABLE":1,"REMARKS":null,"COLUMN_DEF":null,"SQL_DATA_TYPE":12,"SQL_DATETIME_SUB":null,"CHAR_OCTET_LENGTH":30,"ORDINAL_POSITION":52,"IS_NULLABLE":"YES","SS_DATA_TYPE":39}},"User6":{"type":"varchar(30)","field":"User6","null":1,"default":null,"key":"","oem":{"TABLE_QUALIFIER":"eComm","TABLE_OWNER":"dbo","TABLE_NAME":"Orders","COLUMN_NAME":"User6","DATA_TYPE":12,"TYPE_NAME":"varchar","PRECISION":30,"LENGTH":30,"SCALE":null,"RADIX":null,"NULLABLE":1,"REMARKS":null,"COLUMN_DEF":null,"SQL_DATA_TYPE":12,"SQL_DATETIME_SUB":null,"CHAR_OCTET_LENGTH":30,"ORDINAL_POSITION":53,"IS_NULLABLE":"YES","SS_DATA_TYPE":39}},"SoldByName":{"type":"varchar(40)","field":"SoldByName","null":1,"default":null,"key":"","oem":{"TABLE_QUALIFIER":"eComm","TABLE_OWNER":"dbo","TABLE_NAME":"Orders","COLUMN_NAME":"SoldByName","DATA_TYPE":12,"TYPE_NAME":"varchar","PRECISION":40,"LENGTH":40,"SCALE":null,"RADIX":null,"NULLABLE":1,"REMARKS":null,"COLUMN_DEF":null,"SQL_DATA_TYPE":12,"SQL_DATETIME_SUB":null,"CHAR_OCTET_LENGTH":40,"ORDINAL_POSITION":54,"IS_NULLABLE":"YES","SS_DATA_TYPE":39}},"SoldByAddr1":{"type":"varchar(40)","field":"SoldByAddr1","null":1,"default":null,"key":"","oem":{"TABLE_QUALIFIER":"eComm","TABLE_OWNER":"dbo","TABLE_NAME":"Orders","COLUMN_NAME":"SoldByAddr1","DATA_TYPE":12,"TYPE_NAME":"varchar","PRECISION":40,"LENGTH":40,"SCALE":null,"RADIX":null,"NULLABLE":1,"REMARKS":null,"COLUMN_DEF":null,"SQL_DATA_TYPE":12,"SQL_DATETIME_SUB":null,"CHAR_OCTET_LENGTH":40,"ORDINAL_POSITION":55,"IS_NULLABLE":"YES","SS_DATA_TYPE":39}},"SoldByAddr2":{"type":"varchar(40)","field":"SoldByAddr2","null":1,"default":null,"key":"","oem":{"TABLE_QUALIFIER":"eComm","TABLE_OWNER":"dbo","TABLE_NAME":"Orders","COLUMN_NAME":"SoldByAddr2","DATA_TYPE":12,"TYPE_NAME":"varchar","PRECISION":40,"LENGTH":40,"SCALE":null,"RADIX":null,"NULLABLE":1,"REMARKS":null,"COLUMN_DEF":null,"SQL_DATA_TYPE":12,"SQL_DATETIME_SUB":null,"CHAR_OCTET_LENGTH":40,"ORDINAL_POSITION":56,"IS_NULLABLE":"YES","SS_DATA_TYPE":39}},"SoldByCity":{"type":"varchar(20)","field":"SoldByCity","null":1,"default":null,"key":"","oem":{"TABLE_QUALIFIER":"eComm","TABLE_OWNER":"dbo","TABLE_NAME":"Orders","COLUMN_NAME":"SoldByCity","DATA_TYPE":12,"TYPE_NAME":"varchar","PRECISION":20,"LENGTH":20,"SCALE":null,"RADIX":null,"NULLABLE":1,"REMARKS":null,"COLUMN_DEF":null,"SQL_DATA_TYPE":12,"SQL_DATETIME_SUB":null,"CHAR_OCTET_LENGTH":20,"ORDINAL_POSITION":57,"IS_NULLABLE":"YES","SS_DATA_TYPE":39}},"SoldByState":{"type":"varchar(2)","field":"SoldByState","null":1,"default":null,"key":"","oem":{"TABLE_QUALIFIER":"eComm","TABLE_OWNER":"dbo","TABLE_NAME":"Orders","COLUMN_NAME":"SoldByState","DATA_TYPE":12,"TYPE_NAME":"varchar","PRECISION":2,"LENGTH":2,"SCALE":null,"RADIX":null,"NULLABLE":1,"REMARKS":null,"COLUMN_DEF":null,"SQL_DATA_TYPE":12,"SQL_DATETIME_SUB":null,"CHAR_OCTET_LENGTH":2,"ORDINAL_POSITION":58,"IS_NULLABLE":"YES","SS_DATA_TYPE":39}},"SoldByZip":{"type":"varchar(10)","field":"SoldByZip","null":1,"default":null,"key":"","oem":{"TABLE_QUALIFIER":"eComm","TABLE_OWNER":"dbo","TABLE_NAME":"Orders","COLUMN_NAME":"SoldByZip","DATA_TYPE":12,"TYPE_NAME":"varchar","PRECISION":10,"LENGTH":10,"SCALE":null,"RADIX":null,"NULLABLE":1,"REMARKS":null,"COLUMN_DEF":null,"SQL_DATA_TYPE":12,"SQL_DATETIME_SUB":null,"CHAR_OCTET_LENGTH":10,"ORDINAL_POSITION":59,"IS_NULLABLE":"YES","SS_DATA_TYPE":39}},"TotOrderAmt":{"type":"decimal(20, 2)","field":"TotOrderAmt","null":1,"default":null,"key":"","oem":{"TABLE_QUALIFIER":"eComm","TABLE_OWNER":"dbo","TABLE_NAME":"Orders","COLUMN_NAME":"TotOrderAmt","DATA_TYPE":3,"TYPE_NAME":"decimal","PRECISION":18,"LENGTH":20,"SCALE":2,"RADIX":10,"NULLABLE":1,"REMARKS":null,"COLUMN_DEF":null,"SQL_DATA_TYPE":3,"SQL_DATETIME_SUB":null,"CHAR_OCTET_LENGTH":null,"ORDINAL_POSITION":60,"IS_NULLABLE":"YES","SS_DATA_TYPE":106}},"AddHandlingAmt":{"type":"decimal(20, 2)","field":"AddHandlingAmt","null":1,"default":null,"key":"","oem":{"TABLE_QUALIFIER":"eComm","TABLE_OWNER":"dbo","TABLE_NAME":"Orders","COLUMN_NAME":"AddHandlingAmt","DATA_TYPE":3,"TYPE_NAME":"decimal","PRECISION":18,"LENGTH":20,"SCALE":2,"RADIX":10,"NULLABLE":1,"REMARKS":null,"COLUMN_DEF":null,"SQL_DATA_TYPE":3,"SQL_DATETIME_SUB":null,"CHAR_OCTET_LENGTH":null,"ORDINAL_POSITION":61,"IS_NULLABLE":"YES","SS_DATA_TYPE":106}},"User7":{"type":"varchar(100)","field":"User7","null":1,"default":null,"key":"","oem":{"TABLE_QUALIFIER":"eComm","TABLE_OWNER":"dbo","TABLE_NAME":"Orders","COLUMN_NAME":"User7","DATA_TYPE":12,"TYPE_NAME":"varchar","PRECISION":100,"LENGTH":100,"SCALE":null,"RADIX":null,"NULLABLE":1,"REMARKS":null,"COLUMN_DEF":null,"SQL_DATA_TYPE":12,"SQL_DATETIME_SUB":null,"CHAR_OCTET_LENGTH":100,"ORDINAL_POSITION":62,"IS_NULLABLE":"YES","SS_DATA_TYPE":39}},"User8":{"type":"varchar(100)","field":"User8","null":1,"default":null,"key":"","oem":{"TABLE_QUALIFIER":"eComm","TABLE_OWNER":"dbo","TABLE_NAME":"Orders","COLUMN_NAME":"User8","DATA_TYPE":12,"TYPE_NAME":"varchar","PRECISION":100,"LENGTH":100,"SCALE":null,"RADIX":null,"NULLABLE":1,"REMARKS":null,"COLUMN_DEF":null,"SQL_DATA_TYPE":12,"SQL_DATETIME_SUB":null,"CHAR_OCTET_LENGTH":100,"ORDINAL_POSITION":63,"IS_NULLABLE":"YES","SS_DATA_TYPE":39}},"SalesPersonID":{"type":"varchar(10)","field":"SalesPersonID","null":1,"default":null,"key":"","oem":{"TABLE_QUALIFIER":"eComm","TABLE_OWNER":"dbo","TABLE_NAME":"Orders","COLUMN_NAME":"SalesPersonID","DATA_TYPE":12,"TYPE_NAME":"varchar","PRECISION":10,"LENGTH":10,"SCALE":null,"RADIX":null,"NULLABLE":1,"REMARKS":null,"COLUMN_DEF":null,"SQL_DATA_TYPE":12,"SQL_DATETIME_SUB":null,"CHAR_OCTET_LENGTH":10,"ORDINAL_POSITION":64,"IS_NULLABLE":"YES","SS_DATA_TYPE":39}},"TermsDescription":{"type":"varchar(30)","field":"TermsDescription","null":1,"default":null,"key":"","oem":{"TABLE_QUALIFIER":"eComm","TABLE_OWNER":"dbo","TABLE_NAME":"Orders","COLUMN_NAME":"TermsDescription","DATA_TYPE":12,"TYPE_NAME":"varchar","PRECISION":30,"LENGTH":30,"SCALE":null,"RADIX":null,"NULLABLE":1,"REMARKS":null,"COLUMN_DEF":null,"SQL_DATA_TYPE":12,"SQL_DATETIME_SUB":null,"CHAR_OCTET_LENGTH":30,"ORDINAL_POSITION":65,"IS_NULLABLE":"YES","SS_DATA_TYPE":39}},"ShipLoc":{"type":"varchar(25)","field":"ShipLoc","null":1,"default":null,"key":"","oem":{"TABLE_QUALIFIER":"eComm","TABLE_OWNER":"dbo","TABLE_NAME":"Orders","COLUMN_NAME":"ShipLoc","DATA_TYPE":12,"TYPE_NAME":"varchar","PRECISION":25,"LENGTH":25,"SCALE":null,"RADIX":null,"NULLABLE":1,"REMARKS":null,"COLUMN_DEF":null,"SQL_DATA_TYPE":12,"SQL_DATETIME_SUB":null,"CHAR_OCTET_LENGTH":25,"ORDINAL_POSITION":66,"IS_NULLABLE":"YES","SS_DATA_TYPE":39}},"RouteID":{"type":"varchar(20)","field":"RouteID","null":1,"default":null,"key":"","oem":{"TABLE_QUALIFIER":"eComm","TABLE_OWNER":"dbo","TABLE_NAME":"Orders","COLUMN_NAME":"RouteID","DATA_TYPE":12,"TYPE_NAME":"varchar","PRECISION":20,"LENGTH":20,"SCALE":null,"RADIX":null,"NULLABLE":1,"REMARKS":null,"COLUMN_DEF":null,"SQL_DATA_TYPE":12,"SQL_DATETIME_SUB":null,"CHAR_OCTET_LENGTH":20,"ORDINAL_POSITION":67,"IS_NULLABLE":"YES","SS_DATA_TYPE":39}},"StopNumber":{"type":"int(4)","field":"StopNumber","null":1,"default":null,"key":"","oem":{"TABLE_QUALIFIER":"eComm","TABLE_OWNER":"dbo","TABLE_NAME":"Orders","COLUMN_NAME":"StopNumber","DATA_TYPE":4,"TYPE_NAME":"int","PRECISION":10,"LENGTH":4,"SCALE":0,"RADIX":10,"NULLABLE":1,"REMARKS":null,"COLUMN_DEF":null,"SQL_DATA_TYPE":4,"SQL_DATETIME_SUB":null,"CHAR_OCTET_LENGTH":null,"ORDINAL_POSITION":68,"IS_NULLABLE":"YES","SS_DATA_TYPE":38}},"PODDate":{"type":"smalldatetime(16)","field":"PODDate","null":1,"default":null,"key":"","oem":{"TABLE_QUALIFIER":"eComm","TABLE_OWNER":"dbo","TABLE_NAME":"Orders","COLUMN_NAME":"PODDate","DATA_TYPE":11,"TYPE_NAME":"smalldatetime","PRECISION":16,"LENGTH":16,"SCALE":0,"RADIX":null,"NULLABLE":1,"REMARKS":null,"COLUMN_DEF":null,"SQL_DATA_TYPE":9,"SQL_DATETIME_SUB":3,"CHAR_OCTET_LENGTH":null,"ORDINAL_POSITION":69,"IS_NULLABLE":"YES","SS_DATA_TYPE":111}},"InvoiceNumber":{"type":"varchar(20)","field":"InvoiceNumber","null":1,"default":null,"key":"","oem":{"TABLE_QUALIFIER":"eComm","TABLE_OWNER":"dbo","TABLE_NAME":"Orders","COLUMN_NAME":"InvoiceNumber","DATA_TYPE":12,"TYPE_NAME":"varchar","PRECISION":20,"LENGTH":20,"SCALE":null,"RADIX":null,"NULLABLE":1,"REMARKS":null,"COLUMN_DEF":null,"SQL_DATA_TYPE":12,"SQL_DATETIME_SUB":null,"CHAR_OCTET_LENGTH":20,"ORDINAL_POSITION":70,"IS_NULLABLE":"YES","SS_DATA_TYPE":39}},"ShipCountry":{"type":"varchar(30)","field":"ShipCountry","null":1,"default":null,"key":"","oem":{"TABLE_QUALIFIER":"eComm","TABLE_OWNER":"dbo","TABLE_NAME":"Orders","COLUMN_NAME":"ShipCountry","DATA_TYPE":12,"TYPE_NAME":"varchar","PRECISION":30,"LENGTH":30,"SCALE":null,"RADIX":null,"NULLABLE":1,"REMARKS":null,"COLUMN_DEF":null,"SQL_DATA_TYPE":12,"SQL_DATETIME_SUB":null,"CHAR_OCTET_LENGTH":30,"ORDINAL_POSITION":71,"IS_NULLABLE":"YES","SS_DATA_TYPE":39}},"DistCountry":{"type":"varchar(30)","field":"DistCountry","null":1,"default":null,"key":"","oem":{"TABLE_QUALIFIER":"eComm","TABLE_OWNER":"dbo","TABLE_NAME":"Orders","COLUMN_NAME":"DistCountry","DATA_TYPE":12,"TYPE_NAME":"varchar","PRECISION":30,"LENGTH":30,"SCALE":null,"RADIX":null,"NULLABLE":1,"REMARKS":null,"COLUMN_DEF":null,"SQL_DATA_TYPE":12,"SQL_DATETIME_SUB":null,"CHAR_OCTET_LENGTH":30,"ORDINAL_POSITION":72,"IS_NULLABLE":"YES","SS_DATA_TYPE":39}},"SoldByCountry":{"type":"varchar(30)","field":"SoldByCountry","null":1,"default":null,"key":"","oem":{"TABLE_QUALIFIER":"eComm","TABLE_OWNER":"dbo","TABLE_NAME":"Orders","COLUMN_NAME":"SoldByCountry","DATA_TYPE":12,"TYPE_NAME":"varchar","PRECISION":30,"LENGTH":30,"SCALE":null,"RADIX":null,"NULLABLE":1,"REMARKS":null,"COLUMN_DEF":null,"SQL_DATA_TYPE":12,"SQL_DATETIME_SUB":null,"CHAR_OCTET_LENGTH":30,"ORDINAL_POSITION":73,"IS_NULLABLE":"YES","SS_DATA_TYPE":39}},"COD":{"type":"int(4)","field":"COD","null":1,"default":null,"key":"","oem":{"TABLE_QUALIFIER":"eComm","TABLE_OWNER":"dbo","TABLE_NAME":"Orders","COLUMN_NAME":"COD","DATA_TYPE":4,"TYPE_NAME":"int","PRECISION":10,"LENGTH":4,"SCALE":0,"RADIX":10,"NULLABLE":1,"REMARKS":null,"COLUMN_DEF":null,"SQL_DATA_TYPE":4,"SQL_DATETIME_SUB":null,"CHAR_OCTET_LENGTH":null,"ORDINAL_POSITION":74,"IS_NULLABLE":"YES","SS_DATA_TYPE":38}},"ShipAttn":{"type":"varchar(40)","field":"ShipAttn","null":1,"default":null,"key":"","oem":{"TABLE_QUALIFIER":"eComm","TABLE_OWNER":"dbo","TABLE_NAME":"Orders","COLUMN_NAME":"ShipAttn","DATA_TYPE":12,"TYPE_NAME":"varchar","PRECISION":40,"LENGTH":40,"SCALE":null,"RADIX":null,"NULLABLE":1,"REMARKS":null,"COLUMN_DEF":null,"SQL_DATA_TYPE":12,"SQL_DATETIME_SUB":null,"CHAR_OCTET_LENGTH":40,"ORDINAL_POSITION":75,"IS_NULLABLE":"YES","SS_DATA_TYPE":39}},"SiteID":{"type":"varchar(20)","field":"SiteID","null":1,"default":null,"key":"","oem":{"TABLE_QUALIFIER":"eComm","TABLE_OWNER":"dbo","TABLE_NAME":"Orders","COLUMN_NAME":"SiteID","DATA_TYPE":12,"TYPE_NAME":"varchar","PRECISION":20,"LENGTH":20,"SCALE":null,"RADIX":null,"NULLABLE":1,"REMARKS":null,"COLUMN_DEF":null,"SQL_DATA_TYPE":12,"SQL_DATETIME_SUB":null,"CHAR_OCTET_LENGTH":20,"ORDINAL_POSITION":76,"IS_NULLABLE":"YES","SS_DATA_TYPE":39}},"StoreNum":{"type":"varchar(20)","field":"StoreNum","null":1,"default":null,"key":"","oem":{"TABLE_QUALIFIER":"eComm","TABLE_OWNER":"dbo","TABLE_NAME":"Orders","COLUMN_NAME":"StoreNum","DATA_TYPE":12,"TYPE_NAME":"varchar","PRECISION":20,"LENGTH":20,"SCALE":null,"RADIX":null,"NULLABLE":1,"REMARKS":null,"COLUMN_DEF":null,"SQL_DATA_TYPE":12,"SQL_DATETIME_SUB":null,"CHAR_OCTET_LENGTH":20,"ORDINAL_POSITION":77,"IS_NULLABLE":"YES","SS_DATA_TYPE":39}},"Carrier":{"type":"varchar(20)","field":"Carrier","null":1,"default":null,"key":"","oem":{"TABLE_QUALIFIER":"eComm","TABLE_OWNER":"dbo","TABLE_NAME":"Orders","COLUMN_NAME":"Carrier","DATA_TYPE":12,"TYPE_NAME":"varchar","PRECISION":20,"LENGTH":20,"SCALE":null,"RADIX":null,"NULLABLE":1,"REMARKS":null,"COLUMN_DEF":null,"SQL_DATA_TYPE":12,"SQL_DATETIME_SUB":null,"CHAR_OCTET_LENGTH":20,"ORDINAL_POSITION":78,"IS_NULLABLE":"YES","SS_DATA_TYPE":39}},"BackOrderStatus":{"type":"varchar(10)","field":"BackOrderStatus","null":1,"default":null,"key":"","oem":{"TABLE_QUALIFIER":"eComm","TABLE_OWNER":"dbo","TABLE_NAME":"Orders","COLUMN_NAME":"BackOrderStatus","DATA_TYPE":12,"TYPE_NAME":"varchar","PRECISION":10,"LENGTH":10,"SCALE":null,"RADIX":null,"NULLABLE":1,"REMARKS":null,"COLUMN_DEF":null,"SQL_DATA_TYPE":12,"SQL_DATETIME_SUB":null,"CHAR_OCTET_LENGTH":10,"ORDINAL_POSITION":79,"IS_NULLABLE":"YES","SS_DATA_TYPE":39}},"ShipPhone":{"type":"varchar(20)","field":"ShipPhone","null":1,"default":null,"key":"","oem":{"TABLE_QUALIFIER":"eComm","TABLE_OWNER":"dbo","TABLE_NAME":"Orders","COLUMN_NAME":"ShipPhone","DATA_TYPE":12,"TYPE_NAME":"varchar","PRECISION":20,"LENGTH":20,"SCALE":null,"RADIX":null,"NULLABLE":1,"REMARKS":null,"COLUMN_DEF":null,"SQL_DATA_TYPE":12,"SQL_DATETIME_SUB":null,"CHAR_OCTET_LENGTH":20,"ORDINAL_POSITION":80,"IS_NULLABLE":"YES","SS_DATA_TYPE":39}},"DistPhone":{"type":"varchar(20)","field":"DistPhone","null":1,"default":null,"key":"","oem":{"TABLE_QUALIFIER":"eComm","TABLE_OWNER":"dbo","TABLE_NAME":"Orders","COLUMN_NAME":"DistPhone","DATA_TYPE":12,"TYPE_NAME":"varchar","PRECISION":20,"LENGTH":20,"SCALE":null,"RADIX":null,"NULLABLE":1,"REMARKS":null,"COLUMN_DEF":null,"SQL_DATA_TYPE":12,"SQL_DATETIME_SUB":null,"CHAR_OCTET_LENGTH":20,"ORDINAL_POSITION":81,"IS_NULLABLE":"YES","SS_DATA_TYPE":39}},"FreightTerms":{"type":"varchar(20)","field":"FreightTerms","null":1,"default":null,"key":"","oem":{"TABLE_QUALIFIER":"eComm","TABLE_OWNER":"dbo","TABLE_NAME":"Orders","COLUMN_NAME":"FreightTerms","DATA_TYPE":12,"TYPE_NAME":"varchar","PRECISION":20,"LENGTH":20,"SCALE":null,"RADIX":null,"NULLABLE":1,"REMARKS":null,"COLUMN_DEF":null,"SQL_DATA_TYPE":12,"SQL_DATETIME_SUB":null,"CHAR_OCTET_LENGTH":20,"ORDINAL_POSITION":82,"IS_NULLABLE":"YES","SS_DATA_TYPE":39}},"PalletCount":{"type":"int(4)","field":"PalletCount","null":1,"default":null,"key":"","oem":{"TABLE_QUALIFIER":"eComm","TABLE_OWNER":"dbo","TABLE_NAME":"Orders","COLUMN_NAME":"PalletCount","DATA_TYPE":4,"TYPE_NAME":"int","PRECISION":10,"LENGTH":4,"SCALE":0,"RADIX":10,"NULLABLE":1,"REMARKS":null,"COLUMN_DEF":null,"SQL_DATA_TYPE":4,"SQL_DATETIME_SUB":null,"CHAR_OCTET_LENGTH":null,"ORDINAL_POSITION":83,"IS_NULLABLE":"YES","SS_DATA_TYPE":38}},"AltShipperID":{"type":"varchar(20)","field":"AltShipperID","null":1,"default":null,"key":"","oem":{"TABLE_QUALIFIER":"eComm","TABLE_OWNER":"dbo","TABLE_NAME":"Orders","COLUMN_NAME":"AltShipperID","DATA_TYPE":12,"TYPE_NAME":"varchar","PRECISION":20,"LENGTH":20,"SCALE":null,"RADIX":null,"NULLABLE":1,"REMARKS":null,"COLUMN_DEF":null,"SQL_DATA_TYPE":12,"SQL_DATETIME_SUB":null,"CHAR_OCTET_LENGTH":20,"ORDINAL_POSITION":84,"IS_NULLABLE":"YES","SS_DATA_TYPE":39}},"AltShipperType":{"type":"varchar(20)","field":"AltShipperType","null":1,"default":null,"key":"","oem":{"TABLE_QUALIFIER":"eComm","TABLE_OWNER":"dbo","TABLE_NAME":"Orders","COLUMN_NAME":"AltShipperType","DATA_TYPE":12,"TYPE_NAME":"varchar","PRECISION":20,"LENGTH":20,"SCALE":null,"RADIX":null,"NULLABLE":1,"REMARKS":null,"COLUMN_DEF":null,"SQL_DATA_TYPE":12,"SQL_DATETIME_SUB":null,"CHAR_OCTET_LENGTH":20,"ORDINAL_POSITION":85,"IS_NULLABLE":"YES","SS_DATA_TYPE":39}},"AltShipperName":{"type":"varchar(50)","field":"AltShipperName","null":1,"default":null,"key":"","oem":{"TABLE_QUALIFIER":"eComm","TABLE_OWNER":"dbo","TABLE_NAME":"Orders","COLUMN_NAME":"AltShipperName","DATA_TYPE":12,"TYPE_NAME":"varchar","PRECISION":50,"LENGTH":50,"SCALE":null,"RADIX":null,"NULLABLE":1,"REMARKS":null,"COLUMN_DEF":null,"SQL_DATA_TYPE":12,"SQL_DATETIME_SUB":null,"CHAR_OCTET_LENGTH":50,"ORDINAL_POSITION":86,"IS_NULLABLE":"YES","SS_DATA_TYPE":39}},"AltShipperAddr":{"type":"varchar(50)","field":"AltShipperAddr","null":1,"default":null,"key":"","oem":{"TABLE_QUALIFIER":"eComm","TABLE_OWNER":"dbo","TABLE_NAME":"Orders","COLUMN_NAME":"AltShipperAddr","DATA_TYPE":12,"TYPE_NAME":"varchar","PRECISION":50,"LENGTH":50,"SCALE":null,"RADIX":null,"NULLABLE":1,"REMARKS":null,"COLUMN_DEF":null,"SQL_DATA_TYPE":12,"SQL_DATETIME_SUB":null,"CHAR_OCTET_LENGTH":50,"ORDINAL_POSITION":87,"IS_NULLABLE":"YES","SS_DATA_TYPE":39}},"AltShipperCity":{"type":"varchar(20)","field":"AltShipperCity","null":1,"default":null,"key":"","oem":{"TABLE_QUALIFIER":"eComm","TABLE_OWNER":"dbo","TABLE_NAME":"Orders","COLUMN_NAME":"AltShipperCity","DATA_TYPE":12,"TYPE_NAME":"varchar","PRECISION":20,"LENGTH":20,"SCALE":null,"RADIX":null,"NULLABLE":1,"REMARKS":null,"COLUMN_DEF":null,"SQL_DATA_TYPE":12,"SQL_DATETIME_SUB":null,"CHAR_OCTET_LENGTH":20,"ORDINAL_POSITION":88,"IS_NULLABLE":"YES","SS_DATA_TYPE":39}},"AltShipperState":{"type":"varchar(10)","field":"AltShipperState","null":1,"default":null,"key":"","oem":{"TABLE_QUALIFIER":"eComm","TABLE_OWNER":"dbo","TABLE_NAME":"Orders","COLUMN_NAME":"AltShipperState","DATA_TYPE":12,"TYPE_NAME":"varchar","PRECISION":10,"LENGTH":10,"SCALE":null,"RADIX":null,"NULLABLE":1,"REMARKS":null,"COLUMN_DEF":null,"SQL_DATA_TYPE":12,"SQL_DATETIME_SUB":null,"CHAR_OCTET_LENGTH":10,"ORDINAL_POSITION":89,"IS_NULLABLE":"YES","SS_DATA_TYPE":39}},"AltShipperZip":{"type":"varchar(10)","field":"AltShipperZip","null":1,"default":null,"key":"","oem":{"TABLE_QUALIFIER":"eComm","TABLE_OWNER":"dbo","TABLE_NAME":"Orders","COLUMN_NAME":"AltShipperZip","DATA_TYPE":12,"TYPE_NAME":"varchar","PRECISION":10,"LENGTH":10,"SCALE":null,"RADIX":null,"NULLABLE":1,"REMARKS":null,"COLUMN_DEF":null,"SQL_DATA_TYPE":12,"SQL_DATETIME_SUB":null,"CHAR_OCTET_LENGTH":10,"ORDINAL_POSITION":90,"IS_NULLABLE":"YES","SS_DATA_TYPE":39}},"AltShipperCountry":{"type":"varchar(20)","field":"AltShipperCountry","null":1,"default":null,"key":"","oem":{"TABLE_QUALIFIER":"eComm","TABLE_OWNER":"dbo","TABLE_NAME":"Orders","COLUMN_NAME":"AltShipperCountry","DATA_TYPE":12,"TYPE_NAME":"varchar","PRECISION":20,"LENGTH":20,"SCALE":null,"RADIX":null,"NULLABLE":1,"REMARKS":null,"COLUMN_DEF":null,"SQL_DATA_TYPE":12,"SQL_DATETIME_SUB":null,"CHAR_OCTET_LENGTH":20,"ORDINAL_POSITION":91,"IS_NULLABLE":"YES","SS_DATA_TYPE":39}},"EmailAddress":{"type":"varchar(100)","field":"EmailAddress","null":1,"default":null,"key":"","oem":{"TABLE_QUALIFIER":"eComm","TABLE_OWNER":"dbo","TABLE_NAME":"Orders","COLUMN_NAME":"EmailAddress","DATA_TYPE":12,"TYPE_NAME":"varchar","PRECISION":100,"LENGTH":100,"SCALE":null,"RADIX":null,"NULLABLE":1,"REMARKS":null,"COLUMN_DEF":null,"SQL_DATA_TYPE":12,"SQL_DATETIME_SUB":null,"CHAR_OCTET_LENGTH":100,"ORDINAL_POSITION":92,"IS_NULLABLE":"YES","SS_DATA_TYPE":39}},"ProjectID":{"type":"varchar(20)","field":"ProjectID","null":1,"default":null,"key":"","oem":{"TABLE_QUALIFIER":"eComm","TABLE_OWNER":"dbo","TABLE_NAME":"Orders","COLUMN_NAME":"ProjectID","DATA_TYPE":12,"TYPE_NAME":"varchar","PRECISION":20,"LENGTH":20,"SCALE":null,"RADIX":null,"NULLABLE":1,"REMARKS":null,"COLUMN_DEF":null,"SQL_DATA_TYPE":12,"SQL_DATETIME_SUB":null,"CHAR_OCTET_LENGTH":20,"ORDINAL_POSITION":93,"IS_NULLABLE":"YES","SS_DATA_TYPE":39}},"DiscountAmt":{"type":"decimal(20, 6)","field":"DiscountAmt","null":1,"default":null,"key":"","oem":{"TABLE_QUALIFIER":"eComm","TABLE_OWNER":"dbo","TABLE_NAME":"Orders","COLUMN_NAME":"DiscountAmt","DATA_TYPE":3,"TYPE_NAME":"decimal","PRECISION":18,"LENGTH":20,"SCALE":6,"RADIX":10,"NULLABLE":1,"REMARKS":null,"COLUMN_DEF":null,"SQL_DATA_TYPE":3,"SQL_DATETIME_SUB":null,"CHAR_OCTET_LENGTH":null,"ORDINAL_POSITION":94,"IS_NULLABLE":"YES","SS_DATA_TYPE":106}},"PmtAmt":{"type":"decimal(20, 6)","field":"PmtAmt","null":1,"default":null,"key":"","oem":{"TABLE_QUALIFIER":"eComm","TABLE_OWNER":"dbo","TABLE_NAME":"Orders","COLUMN_NAME":"PmtAmt","DATA_TYPE":3,"TYPE_NAME":"decimal","PRECISION":18,"LENGTH":20,"SCALE":6,"RADIX":10,"NULLABLE":1,"REMARKS":null,"COLUMN_DEF":null,"SQL_DATA_TYPE":3,"SQL_DATETIME_SUB":null,"CHAR_OCTET_LENGTH":null,"ORDINAL_POSITION":95,"IS_NULLABLE":"YES","SS_DATA_TYPE":106}},"SalesTaxAmt":{"type":"decimal(20, 6)","field":"SalesTaxAmt","null":1,"default":null,"key":"","oem":{"TABLE_QUALIFIER":"eComm","TABLE_OWNER":"dbo","TABLE_NAME":"Orders","COLUMN_NAME":"SalesTaxAmt","DATA_TYPE":3,"TYPE_NAME":"decimal","PRECISION":18,"LENGTH":20,"SCALE":6,"RADIX":10,"NULLABLE":1,"REMARKS":null,"COLUMN_DEF":null,"SQL_DATA_TYPE":3,"SQL_DATETIME_SUB":null,"CHAR_OCTET_LENGTH":null,"ORDINAL_POSITION":96,"IS_NULLABLE":"YES","SS_DATA_TYPE":106}},"CancelDate":{"type":"smalldatetime(16)","field":"CancelDate","null":1,"default":null,"key":"","oem":{"TABLE_QUALIFIER":"eComm","TABLE_OWNER":"dbo","TABLE_NAME":"Orders","COLUMN_NAME":"CancelDate","DATA_TYPE":11,"TYPE_NAME":"smalldatetime","PRECISION":16,"LENGTH":16,"SCALE":0,"RADIX":null,"NULLABLE":1,"REMARKS":null,"COLUMN_DEF":null,"SQL_DATA_TYPE":9,"SQL_DATETIME_SUB":3,"CHAR_OCTET_LENGTH":null,"ORDINAL_POSITION":97,"IS_NULLABLE":"YES","SS_DATA_TYPE":111}},"PrintDate":{"type":"smalldatetime(16)","field":"PrintDate","null":1,"default":null,"key":"","oem":{"TABLE_QUALIFIER":"eComm","TABLE_OWNER":"dbo","TABLE_NAME":"Orders","COLUMN_NAME":"PrintDate","DATA_TYPE":11,"TYPE_NAME":"smalldatetime","PRECISION":16,"LENGTH":16,"SCALE":0,"RADIX":null,"NULLABLE":1,"REMARKS":null,"COLUMN_DEF":null,"SQL_DATA_TYPE":9,"SQL_DATETIME_SUB":3,"CHAR_OCTET_LENGTH":null,"ORDINAL_POSITION":98,"IS_NULLABLE":"YES","SS_DATA_TYPE":111}},"PrintTime":{"type":"smalldatetime(16)","field":"PrintTime","null":1,"default":null,"key":"","oem":{"TABLE_QUALIFIER":"eComm","TABLE_OWNER":"dbo","TABLE_NAME":"Orders","COLUMN_NAME":"PrintTime","DATA_TYPE":11,"TYPE_NAME":"smalldatetime","PRECISION":16,"LENGTH":16,"SCALE":0,"RADIX":null,"NULLABLE":1,"REMARKS":null,"COLUMN_DEF":null,"SQL_DATA_TYPE":9,"SQL_DATETIME_SUB":3,"CHAR_OCTET_LENGTH":null,"ORDINAL_POSITION":99,"IS_NULLABLE":"YES","SS_DATA_TYPE":111}},"PrintOperID":{"type":"varchar(20)","field":"PrintOperID","null":1,"default":null,"key":"","oem":{"TABLE_QUALIFIER":"eComm","TABLE_OWNER":"dbo","TABLE_NAME":"Orders","COLUMN_NAME":"PrintOperID","DATA_TYPE":12,"TYPE_NAME":"varchar","PRECISION":20,"LENGTH":20,"SCALE":null,"RADIX":null,"NULLABLE":1,"REMARKS":null,"COLUMN_DEF":null,"SQL_DATA_TYPE":12,"SQL_DATETIME_SUB":null,"CHAR_OCTET_LENGTH":20,"ORDINAL_POSITION":100,"IS_NULLABLE":"YES","SS_DATA_TYPE":39}},"PalletsIn":{"type":"int(4)","field":"PalletsIn","null":1,"default":null,"key":"","oem":{"TABLE_QUALIFIER":"eComm","TABLE_OWNER":"dbo","TABLE_NAME":"Orders","COLUMN_NAME":"PalletsIn","DATA_TYPE":4,"TYPE_NAME":"int","PRECISION":10,"LENGTH":4,"SCALE":0,"RADIX":10,"NULLABLE":1,"REMARKS":null,"COLUMN_DEF":null,"SQL_DATA_TYPE":4,"SQL_DATETIME_SUB":null,"CHAR_OCTET_LENGTH":null,"ORDINAL_POSITION":101,"IS_NULLABLE":"YES","SS_DATA_TYPE":38}},"PalletsOut":{"type":"int(4)","field":"PalletsOut","null":1,"default":null,"key":"","oem":{"TABLE_QUALIFIER":"eComm","TABLE_OWNER":"dbo","TABLE_NAME":"Orders","COLUMN_NAME":"PalletsOut","DATA_TYPE":4,"TYPE_NAME":"int","PRECISION":10,"LENGTH":4,"SCALE":0,"RADIX":10,"NULLABLE":1,"REMARKS":null,"COLUMN_DEF":null,"SQL_DATA_TYPE":4,"SQL_DATETIME_SUB":null,"CHAR_OCTET_LENGTH":null,"ORDINAL_POSITION":102,"IS_NULLABLE":"YES","SS_DATA_TYPE":38}},"TruckTemp":{"type":"int(4)","field":"TruckTemp","null":1,"default":null,"key":"","oem":{"TABLE_QUALIFIER":"eComm","TABLE_OWNER":"dbo","TABLE_NAME":"Orders","COLUMN_NAME":"TruckTemp","DATA_TYPE":4,"TYPE_NAME":"int","PRECISION":10,"LENGTH":4,"SCALE":0,"RADIX":10,"NULLABLE":1,"REMARKS":null,"COLUMN_DEF":null,"SQL_DATA_TYPE":4,"SQL_DATETIME_SUB":null,"CHAR_OCTET_LENGTH":null,"ORDINAL_POSITION":103,"IS_NULLABLE":"YES","SS_DATA_TYPE":38}},"ShipAddr3":{"type":"varchar(40)","field":"ShipAddr3","null":1,"default":null,"key":"","oem":{"TABLE_QUALIFIER":"eComm","TABLE_OWNER":"dbo","TABLE_NAME":"Orders","COLUMN_NAME":"ShipAddr3","DATA_TYPE":12,"TYPE_NAME":"varchar","PRECISION":40,"LENGTH":40,"SCALE":null,"RADIX":null,"NULLABLE":1,"REMARKS":null,"COLUMN_DEF":null,"SQL_DATA_TYPE":12,"SQL_DATETIME_SUB":null,"CHAR_OCTET_LENGTH":40,"ORDINAL_POSITION":104,"IS_NULLABLE":"YES","SS_DATA_TYPE":39}},"ShipAddr4":{"type":"varchar(40)","field":"ShipAddr4","null":1,"default":null,"key":"","oem":{"TABLE_QUALIFIER":"eComm","TABLE_OWNER":"dbo","TABLE_NAME":"Orders","COLUMN_NAME":"ShipAddr4","DATA_TYPE":12,"TYPE_NAME":"varchar","PRECISION":40,"LENGTH":40,"SCALE":null,"RADIX":null,"NULLABLE":1,"REMARKS":null,"COLUMN_DEF":null,"SQL_DATA_TYPE":12,"SQL_DATETIME_SUB":null,"CHAR_OCTET_LENGTH":40,"ORDINAL_POSITION":105,"IS_NULLABLE":"YES","SS_DATA_TYPE":39}},"ReleaseDate":{"type":"smalldatetime(16)","field":"ReleaseDate","null":1,"default":null,"key":"","oem":{"TABLE_QUALIFIER":"eComm","TABLE_OWNER":"dbo","TABLE_NAME":"Orders","COLUMN_NAME":"ReleaseDate","DATA_TYPE":11,"TYPE_NAME":"smalldatetime","PRECISION":16,"LENGTH":16,"SCALE":0,"RADIX":null,"NULLABLE":1,"REMARKS":null,"COLUMN_DEF":null,"SQL_DATA_TYPE":9,"SQL_DATETIME_SUB":3,"CHAR_OCTET_LENGTH":null,"ORDINAL_POSITION":106,"IS_NULLABLE":"YES","SS_DATA_TYPE":111}},"ReleaseTime":{"type":"smalldatetime(16)","field":"ReleaseTime","null":1,"default":null,"key":"","oem":{"TABLE_QUALIFIER":"eComm","TABLE_OWNER":"dbo","TABLE_NAME":"Orders","COLUMN_NAME":"ReleaseTime","DATA_TYPE":11,"TYPE_NAME":"smalldatetime","PRECISION":16,"LENGTH":16,"SCALE":0,"RADIX":null,"NULLABLE":1,"REMARKS":null,"COLUMN_DEF":null,"SQL_DATA_TYPE":9,"SQL_DATETIME_SUB":3,"CHAR_OCTET_LENGTH":null,"ORDINAL_POSITION":107,"IS_NULLABLE":"YES","SS_DATA_TYPE":111}},"ShipConfUser1":{"type":"varchar(30)","field":"ShipConfUser1","null":1,"default":null,"key":"","oem":{"TABLE_QUALIFIER":"eComm","TABLE_OWNER":"dbo","TABLE_NAME":"Orders","COLUMN_NAME":"ShipConfUser1","DATA_TYPE":12,"TYPE_NAME":"varchar","PRECISION":30,"LENGTH":30,"SCALE":null,"RADIX":null,"NULLABLE":1,"REMARKS":null,"COLUMN_DEF":null,"SQL_DATA_TYPE":12,"SQL_DATETIME_SUB":null,"CHAR_OCTET_LENGTH":30,"ORDINAL_POSITION":108,"IS_NULLABLE":"YES","SS_DATA_TYPE":39}},"ShipConfUser2":{"type":"varchar(30)","field":"ShipConfUser2","null":1,"default":null,"key":"","oem":{"TABLE_QUALIFIER":"eComm","TABLE_OWNER":"dbo","TABLE_NAME":"Orders","COLUMN_NAME":"ShipConfUser2","DATA_TYPE":12,"TYPE_NAME":"varchar","PRECISION":30,"LENGTH":30,"SCALE":null,"RADIX":null,"NULLABLE":1,"REMARKS":null,"COLUMN_DEF":null,"SQL_DATA_TYPE":12,"SQL_DATETIME_SUB":null,"CHAR_OCTET_LENGTH":30,"ORDINAL_POSITION":109,"IS_NULLABLE":"YES","SS_DATA_TYPE":39}}}